beaverfe/__init__.py
beaverfe/auto_feature_pipeline.py
beaverfe/beaver_pipeline.py
beaverfe/evaluate_transformations.py
beaverfe/auto_parameters/__init__.py
beaverfe/auto_parameters/categorical_features/__init__.py
beaverfe/auto_parameters/categorical_features/categorical_enconding.py
beaverfe/auto_parameters/distribution_n_scale/__init__.py
beaverfe/auto_parameters/distribution_n_scale/non_linear_transformation.py
beaverfe/auto_parameters/distribution_n_scale/normalization.py
beaverfe/auto_parameters/distribution_n_scale/quantile_transformation.py
beaverfe/auto_parameters/distribution_n_scale/scale_transformation.py
beaverfe/auto_parameters/features_reduction/__init__.py
beaverfe/auto_parameters/features_reduction/column_selection.py
beaverfe/auto_parameters/features_reduction/dimensionality_reduction.py
beaverfe/auto_parameters/missing_n_outliers/__init__.py
beaverfe/auto_parameters/missing_n_outliers/missing_values_handler.py
beaverfe/auto_parameters/missing_n_outliers/missing_values_indicator.py
beaverfe/auto_parameters/missing_n_outliers/outliers_handler.py
beaverfe/auto_parameters/numerical_features/__init__.py
beaverfe/auto_parameters/numerical_features/mathematical_operations.py
beaverfe/auto_parameters/numerical_features/numerical_binning.py
beaverfe/auto_parameters/numerical_features/spline_transformation.py
beaverfe/auto_parameters/periodic_features/__init__.py
beaverfe/auto_parameters/periodic_features/cyclical_features_transformer.py
beaverfe/auto_parameters/periodic_features/datetime_transformer.py
beaverfe/auto_parameters/shared/__init__.py
beaverfe/auto_parameters/shared/evaluate_model/__init__.py
beaverfe/auto_parameters/shared/evaluate_model/evaluate_model.py
beaverfe/auto_parameters/shared/feature_selector/__init__.py
beaverfe/auto_parameters/shared/feature_selector/permutation_rfecv.py
beaverfe/auto_parameters/shared/utils/__init__.py
beaverfe/auto_parameters/shared/utils/is_score_improved.py
beaverfe/transformations/__init__.py
beaverfe-0.4.0.dist-info/METADATA
beaverfe-0.4.0.dist-info/WHEEL
beaverfe-0.4.0.dist-info/RECORD
