Metadata-Version: 2.4
Name: beaverfe
Version: 0.4.0
Summary: A Versatile Toolkit for Automated Feature Engineering in Machine Learning
Author-email: Andres Di Giovanni <andresdigiovanni@gmail.com>
License-Expression: MIT
Keywords: AutoML,automated feature engineering,data preprocessing,data transformation,machine learning pipeline,scikit-learn transformers
Requires-Python: >=3.11
Requires-Dist: category-encoders>=2.6.3
Requires-Dist: pandas>=2.2.2
Requires-Dist: rich>=14.0.0
Requires-Dist: scikit-learn>=1.5.0
